[
  {
    "name": "Neophyte level",
    "minSkillLevel": 0,
    "maxSkillLevel": 19,
    "outputQuality": {
      "Awful": 0.35,
      "Poor": 0.65
    }
  },
  {
    "name": "Novice level",
    "minSkillLevel": 20,
    "maxSkillLevel": 39,
    "outputQuality": {
      "Awful": 0.1,
      "Poor": 0.5,
      "Standard": 0.4
    }
  },
  {
    "name": "Apprentice level",
    "minSkillLevel": 40,
    "maxSkillLevel": 49,
    "outputQuality": {
      "Poor": 0.25,
      "Standard": 0.75
    }
  },
  {
    "name": "Journeyman level",
    "minSkillLevel": 50,
    "maxSkillLevel": 59,
    "outputQuality": {
      "Poor": 0.1,
      "Standard": 0.7,
      "Superior": 0.2
    }
  },
  {
    "name": "Adept level",
    "minSkillLevel": 60,
    "maxSkillLevel": 69,
    "outputQuality": {
      "Poor": 0.05,
      "Standard": 0.45,
      "Superior": 0.5
    }
  },
  {
    "name": "Skilled level",
    "minSkillLevel": 70,
    "maxSkillLevel": 79,
    "outputQuality": {
      "Standard": 0.35,
      "Superior": 0.6,
      "Masterwork": 0.05
    }
  },
  {
    "name": "Expert level",
    "minSkillLevel": 80,
    "maxSkillLevel": 89,
    "outputQuality": {
      "Standard": 0.25,
      "Superior": 0.65,
      "Masterwork": 0.1
    }
  },
  {
    "name": "Master level",
    "minSkillLevel": 90,
    "maxSkillLevel": 99,
    "outputQuality": {
      "Standard": 0.15,
      "Superior": 0.5,
      "Masterwork": 0.35
    }
  },
  {
    "name": "Grandmaster level",
    "minSkillLevel": 100,
    "maxSkillLevel": 100,
    "outputQuality": {
      "Superior": 0.55,
      "Masterwork": 0.45
    }
  }
]